hcolor/__init__.py
hcolor/__version__.py
hcolor/_hcolor.py
hcolor/_names.py
hcolor/_utils.py
hcolor-0.0.7.dist-info/licenses/LICENSE.md
hcolor-0.0.7.dist-info/METADATA
hcolor-0.0.7.dist-info/WHEEL
hcolor-0.0.7.dist-info/top_level.txt
hcolor-0.0.7.dist-info/RECORD
